movoid_function/__init__.py
movoid_function/check.py
movoid_function/decorator.py
movoid_function/function.py
movoid_function/stack.py
movoid_function/type.py
movoid_function-1.8.8.dist-info/METADATA
movoid_function-1.8.8.dist-info/WHEEL
movoid_function-1.8.8.dist-info/top_level.txt
movoid_function-1.8.8.dist-info/RECORD
