Metadata-Version: 2.4
Name: movoid_function
Version: 1.8.8
Home-page: 
Author: movoid
Author-email: bobrobotsun@163.com
Dynamic: author
Dynamic: author-email
Dynamic: description
Dynamic: description-content-type
